zendesk_ticket_viewer/__init__.py
zendesk_ticket_viewer/api.py
zendesk_ticket_viewer/main.py
zendesk_ticket_viewer/ticket.py
zendesk_ticket_viewer-0.5.dist-info/DESCRIPTION.rst
zendesk_ticket_viewer-0.5.dist-info/METADATA
zendesk_ticket_viewer-0.5.dist-info/RECORD
zendesk_ticket_viewer-0.5.dist-info/WHEEL
zendesk_ticket_viewer-0.5.dist-info/metadata.json
zendesk_ticket_viewer-0.5.dist-info/top_level.txt
