Metadata-Version: 2.0
Name: zendesk-ticket-viewer
Version: 0.5
Summary: A command line tool to view Zendesk tickets
Home-page: UNKNOWN
Author: Louis Stekhoven-Smith
Author-email: louis.stekhoven@gmail.com
License: GPL-3.0
Platform: UNKNOWN
Requires-Dist: requests
Requires-Dist: zdesk
Requires-Dist: pytest
